<?xml version="1.0" encoding="UTF-8" standalone="no"?>
<catalog prefer="public" xmlns="urn:oasis:names:tc:entity:xmlns:xml:catalog">
    <uri id="Imports Wizard Entry" name="http://www.isa.us.es/ontologies/RFCSimplified.owl" uri="RFCSimplified.owl"/>
    <uri id="Imports Wizard Entry" name="http://www.isa.us.es/ontologies/RFCSimplifiedAndPPIs-ppinot-relationships.owl" uri="RFCSimplified.owl"/>
    <uri id="Imports Wizard Entry" name="http://www.isa.us.es/ontologies/bpmn.owl" uri="bpmn.owl"/>
    <uri id="Imports Wizard Entry" name="http://www.isa.us.es/ontologies/RFCSimplified-PPIs.owl" uri="RFCSimplified-PPIs.owl"/>
    <uri id="Imports Wizard Entry" name="http://www.isa.us.es/ontologies/RFCSimplifiedAndPPIs-ppinot-relationships.owl" uri="RFCSimplifiedAndPPIs-ppinot-relationships.owl"/>
    <uri id="Imports Wizard Entry" name="http://www.isa.us.es/ontologies/AbstractBP-relationships.owl" uri="AbstractBP-relationships.owl"/>
    <uri id="Imports Wizard Entry" name="http://www.isa.us.es/ontologies/AbstractBP-rules.owl" uri="AbstractBP-rules.owl"/>
    <uri id="Imports Wizard Entry" name="http://www.isa.us.es/ontologies/AbstractBP.owl" uri="AbstractBP.owl"/>
    <uri id="Imports Wizard Entry" name="http://www.isa.us.es/ontologies/ppinot.owl" uri="ppinot.owl"/>
    <uri id="Imports Wizard Entry" name="http://www.isa.us.es/ontologies/ppinot-relationships.owl" uri="ppinot-relationships.owl"/>
    <uri id="Imports Wizard Entry" name="http://www.isa.us.es/ontologies/ppinot-filter.owl" uri="ppinot-filter.owl"/>
    <uri id="Imports Wizard Entry" name="http://www.isa.us.es/ontologies/ppinot-rules.owl" uri="ppinot-rules.owl"/>
</catalog>
